sqlift/__init__.py
sqlift/clients.py
sqlift/exceptions.py
sqlift/main.py
sqlift-0.2.3.dist-info/LICENSE
sqlift-0.2.3.dist-info/METADATA
sqlift-0.2.3.dist-info/WHEEL
sqlift-0.2.3.dist-info/entry_points.txt
sqlift-0.2.3.dist-info/RECORD
