Metadata-Version: 2.3
Name: SQLift
Version: 0.2.3
Summary: Simple CLI migration tool for SQL databases
License: MIT
Keywords: cli,postgres,sql,database,sqlite,postgresql,migration,sqlite3
Author: SpaceShaman
Author-email: spaceshaman@tuta.io
Requires-Python: >=3.10,<4
Classifier: License :: OSI Approved :: MIT License
Classifier: Programming Language :: Python :: 3
Classifier: Programming Language :: Python :: 3.10
Classifier: Programming Language :: Python :: 3.11
Classifier: Programming Language :: Python :: 3.12
Classifier: Programming Language :: Python :: 3.13
Classifier: Programming Language :: SQL
Provides-Extra: postgres
Requires-Dist: psycopg[binary] (>=3,<4) ; extra == "postgres"
Requires-Dist: typer (>=0.15,<0.16)
Project-URL: Documentation, https://github.com/SpaceShaman/SQLift
Project-URL: Homepage, https://github.com/SpaceShaman/SQLift
Project-URL: Repository, https://github.com/SpaceShaman/SQLift
